Metadata-Version: 2.1
Name: picos-sphinx-theme
Version: 0.0.34
Summary: A Sphinx theme for the PICOS documentation.
Home-page: UNKNOWN
Author: PICOS Developers
Author-email: incoming+picos-api/picos@incoming.gitlab.com
License: Apache License 2.0
Project-URL: Example, https://picos-api.gitlab.io/picos/
Project-URL: Source, https://gitlab.com/picos-api/picos-sphinx-theme
Platform: UNKNOWN
Classifier: Framework :: Sphinx :: Theme
Classifier: Topic :: Documentation :: Sphinx
Classifier: License :: OSI Approved :: Apache Software License
Classifier: Operating System :: OS Independent
